conplyent/__init__.py
conplyent/_decorators.py
conplyent/_general.py
conplyent/_msg.py
conplyent/_zmq_pair.py
conplyent/client.py
conplyent/console.py
conplyent/exceptions.py
conplyent/options.py
conplyent/server.py
conplyent-0.2.17.dist-info/METADATA
conplyent-0.2.17.dist-info/RECORD
conplyent-0.2.17.dist-info/WHEEL
conplyent-0.2.17.dist-info/entry_points.txt
conplyent-0.2.17.dist-info/top_level.txt
conplyent_scripts/__init__.py
conplyent_scripts/cli.py
