Metadata-Version: 2.1
Name: conplyent
Version: 0.2.17
Summary: Local and Remote Console executor
Home-page: https://github.com/joshijayesh/conplyent/
Author: Jayesh Joshi
Author-email: jayeshjo1@utexas.edu
License: MIT
Platform: UNKNOWN
Requires-Python: >=3.4.3
Requires-Dist: pyzmq (>=18.1.0)
Requires-Dist: click (>=7.0)
Requires-Dist: psutil (>=5.4.5)
